MANIFEST.in
README.rst
setup.py
cmsplugin_team/__init__.py
cmsplugin_team/cms_plugins.py
cmsplugin_team/models.py
cmsplugin_team/utils.py
cmsplugin_team.egg-info/PKG-INFO
cmsplugin_team.egg-info/SOURCES.txt
cmsplugin_team.egg-info/dependency_links.txt
cmsplugin_team.egg-info/requires.txt
cmsplugin_team.egg-info/top_level.txt
cmsplugin_team/migrations/0001_initial.py
cmsplugin_team/migrations/__init__.py
cmsplugin_team/templates/cms/plugins/team/team.html