Metadata-Version: 1.1
Name: cmsplugin-team
Version: 0.1.0
Summary: Django CMS plugin to list team members/employees.
Home-page: http://github.com/littlepea/cmsplugin-team
Author: Evgeny Demchenko
Author-email: evgeny.demchenko@gmail.com
License: BSD
Platform: UNKNOWN
Provides: cmsplugin_team
